factpy/__init__.py
factpy/__main__.py
factpy/assembling_machines.py
factpy/belts.py
factpy/bus.py
factpy/calculators.py
factpy/circuits.py
factpy/crafting_components.py
factpy/electric_poles.py
factpy/furnaces.py
factpy/inserters.py
factpy/material_types.py
factpy/modules.py
factpy/natural_resources.py
factpy/nuclear.py
factpy/oil_products.py
factpy/pipes.py
factpy/plates.py
factpy/player.py
factpy/resource_extraction.py
factpy/rocket_parts.py
factpy/sciences.py
factpy-0.1.0.dist-info/entry_points.txt
factpy-0.1.0.dist-info/WHEEL
factpy-0.1.0.dist-info/METADATA
factpy-0.1.0.dist-info/RECORD
