Metadata-Version: 2.1
Name: factpy
Version: 0.1.0
Summary: Calculator for the game Factorio
Author: Jels Boulangier
Author-email: boulangier.jels@gmail.com
Requires-Python: >=3.6,<4.0
Classifier: Programming Language :: Python :: 3
Classifier: Programming Language :: Python :: 3.6
Classifier: Programming Language :: Python :: 3.7
Classifier: Programming Language :: Python :: 3.8
